downloaderx/__init__.py
downloaderx/common.py
downloaderx/file/__init__.py
downloaderx/file/common.py
downloaderx/file/errors.py
downloaderx/file/file_downloader.py
downloaderx/file/range_downloader.py
downloaderx/file/segment.py
downloaderx/file/utils.py
downloaderx/file/value_signal.py
downloaderx/files_group.py
downloaderx/invoker.py
downloaderx/retry.py
downloaderx/safe_passage.py
downloaderx/type.py
downloaderx/utils.py
downloaderx-0.1.7.dist-info/LICENSE
downloaderx-0.1.7.dist-info/METADATA
downloaderx-0.1.7.dist-info/WHEEL
downloaderx-0.1.7.dist-info/RECORD
