Metadata-Version: 2.3
Name: downloaderx
Version: 0.1.7
Summary: 
License: MIT
Author: Tao Zeyu
Author-email: i@taozeyu.com
Requires-Python: >=3.10,<3.13
Classifier: License :: OSI Approved :: MIT License
Classifier: Programming Language :: Python :: 3
Classifier: Programming Language :: Python :: 3.10
Classifier: Programming Language :: Python :: 3.11
Classifier: Programming Language :: Python :: 3.12
Requires-Dist: requests (>=2.32.4,<3.0.0)
